{"cameraMode":{"drawMode":0,"name":"Shaded","section":"Shading Mode"},"sceneLighting":true,"audioPlay":false,"sceneViewState":{"showFog":true,"showMaterialUpdate":false,"showSkybox":true,"showFlares":true,"showImageEffects":true,"showParticleSystems":true},"in2DMode":false,"pivot":{"x":104.69986724853516,"y":174.64907836914063,"z":-89.16525268554688},"rotation":{"x":-0.2522825002670288,"y":0.04410429298877716,"z":-0.011511354707181454,"w":-0.9665796160697937},"size":195.71067810058595,"orthographic":false}